.gitignore
.travis.yml
README.rst
setup.py
aubergine/__init__.py
aubergine/aubergine.py
aubergine/common.py
aubergine/decoders.py
aubergine/extractors.py
aubergine/handlers.py
aubergine/utils.py
aubergine.egg-info/PKG-INFO
aubergine.egg-info/SOURCES.txt
aubergine.egg-info/dependency_links.txt
aubergine.egg-info/requires.txt
aubergine.egg-info/top_level.txt
doc/Makefile
doc/make.bat
doc/source/conf.py
doc/source/index.rst
tests/__init__.py
tests/common_fixtures.py
tests/test_aubergine.py
tests/test_common.py
tests/test_create_handler.py
tests/test_decoders.py
tests/test_extractor_builder.py
tests/test_extractors.py
tests/test_handlers.py
tests/test_utils.py