Metadata-Version: 1.0
Name: aubergine
Version: 0.1.2
Summary: aubergine: create REST APIs using API-first approach.
Home-page: UNKNOWN
Author: Konrad Jałowiecki <dexter2206@gmail.com>
Author-email: dexter2206@gmail.com
License: MIT
Keywords: openapi rest api
Platform: Linux
Platform: Unix
